qckt/Canvas.py
qckt/Gates.py
qckt/Job.py
qckt/QCkt.py
qckt/Registers.py
qckt/__init__.py
qckt/qException.py
qckt/backend/BackendAPI.py
qckt/backend/QSystems.py
qckt/backend/__init__.py
qckt/backend/svcReg.py
qckt/gatesutils/GatesUtils.py
qckt/gatesutils/__init__.py
qckt/noisemodel/__init__.py
qckt/noisemodel/noiseChannels.py
qckt/noisemodel/noiseUtils.py
qucircuit-2.2.dist-info/LICENSE
qucircuit-2.2.dist-info/METADATA
qucircuit-2.2.dist-info/WHEEL
qucircuit-2.2.dist-info/top_level.txt
qucircuit-2.2.dist-info/RECORD
