Metadata-Version: 2.1
Name: qucircuit
Version: 2.2
Summary: Quantum computer programming with circuits paradigm
Home-page: https://github.com/atulvarshneya/quantum-computing
Author: Atul Varshneya
Author-email: atul.varshneya@gmail.com
License: GPL
Keywords: qsystems quantum computing
Requires-Python: >3.9
License-File: LICENSE
Requires-Dist: numpy
Requires-Dist: qusimulator (>=2.2)
